macsdk/__init__.py
macsdk/_version.py
macsdk/prompts.py
macsdk/py.typed
macsdk/agents/__init__.py
macsdk/agents/formatter/__init__.py
macsdk/agents/formatter/agent.py
macsdk/agents/formatter/prompts.py
macsdk/agents/rag/__init__.py
macsdk/agents/rag/agent.py
macsdk/agents/rag/cache.py
macsdk/agents/rag/config.py
macsdk/agents/rag/glossary.py
macsdk/agents/rag/graph.py
macsdk/agents/rag/indexer.py
macsdk/agents/rag/models.py
macsdk/agents/rag/nodes.py
macsdk/agents/rag/prompts.py
macsdk/agents/rag/recursive_loader.py
macsdk/agents/supervisor/__init__.py
macsdk/agents/supervisor/agent.py
macsdk/agents/supervisor/prompts.py
macsdk/cli/__init__.py
macsdk/cli/main.py
macsdk/cli/utils.py
macsdk/cli/commands/__init__.py
macsdk/cli/commands/add.py
macsdk/cli/commands/list_cmd.py
macsdk/cli/commands/new.py
macsdk/cli/templates/__init__.py
macsdk/cli/templates/agent/README.md.j2
macsdk/cli/templates/agent/__init__.py.j2
macsdk/cli/templates/agent/agent.py.j2
macsdk/cli/templates/agent/cli.py.j2
macsdk/cli/templates/agent/config.py.j2
macsdk/cli/templates/agent/config.yml.example.j2
macsdk/cli/templates/agent/env.example.j2
macsdk/cli/templates/agent/models.py.j2
macsdk/cli/templates/agent/py.typed.j2
macsdk/cli/templates/agent/pyproject.toml.j2
macsdk/cli/templates/agent/test_agent.py.j2
macsdk/cli/templates/agent/tools.py.j2
macsdk/cli/templates/agent/facts/example-fact.md.j2
macsdk/cli/templates/agent/skills/example-skill.md.j2
macsdk/cli/templates/chatbot/README.md.j2
macsdk/cli/templates/chatbot/__init__.py.j2
macsdk/cli/templates/chatbot/__main__.py.j2
macsdk/cli/templates/chatbot/agents.py.j2
macsdk/cli/templates/chatbot/cli.py.j2
macsdk/cli/templates/chatbot/config.py.j2
macsdk/cli/templates/chatbot/config.yml.example.j2
macsdk/cli/templates/chatbot/env.example.j2
macsdk/cli/templates/chatbot/prompts.py.j2
macsdk/cli/templates/chatbot/py.typed.j2
macsdk/cli/templates/chatbot/pyproject.toml.j2
macsdk/cli/templates/chatbot/static/index.html.j2
macsdk-0.11.1.dist-info/METADATA
macsdk-0.11.1.dist-info/WHEEL
macsdk-0.11.1.dist-info/entry_points.txt
macsdk-0.11.1.dist-info/RECORD
