Metadata-Version: 2.4
Name: macsdk
Version: 0.11.1
Summary: Multi-Agent Chatbot SDK - Build customizable multi-agent chatbots with ease
Project-URL: Homepage, https://github.com/juanje/macsdk
Project-URL: Documentation, https://github.com/juanje/macsdk#readme
Project-URL: Repository, https://github.com/juanje/macsdk
Author-email: Juanje Ojeda <juanje@redhat.com>
License: MIT
Keywords: ai,chatbot,langchain,langgraph,llm,multi-agent,sdk
Classifier: Development Status :: 3 - Alpha
Classifier: Intended Audience :: Developers
Classifier: License :: OSI Approved :: MIT License
Classifier: Programming Language :: Python :: 3.12
Classifier: Programming Language :: Python :: 3.13
Classifier: Topic :: Scientific/Engineering :: Artificial Intelligence
Requires-Python: >=3.12
Requires-Dist: aiofiles>=24.0.0
Requires-Dist: click>=8.0.0
Requires-Dist: fastapi>=0.115.0
Requires-Dist: httpx>=0.27.0
Requires-Dist: jinja2>=3.0.0
Requires-Dist: jsonpath-ng>=1.6.0
Requires-Dist: langchain-core>=1.0.0
Requires-Dist: langchain-google-genai>=2.0.0
Requires-Dist: langchain>=1.0.1
Requires-Dist: langgraph>=1.0.0
Requires-Dist: pydantic-settings>=2.0.0
Requires-Dist: pydantic>=2.0.0
Requires-Dist: pyyaml>=6.0.0
Requires-Dist: rich>=13.0.0
Requires-Dist: simpleeval>=1.0.0
Requires-Dist: twine>=6.2.0
Requires-Dist: uvicorn>=0.32.0
Requires-Dist: websockets>=13.0
Provides-Extra: all
Requires-Dist: beautifulsoup4>=4.12.0; extra == 'all'
Requires-Dist: certifi>=2023.0.0; extra == 'all'
Requires-Dist: chromadb>=0.4.0; extra == 'all'
Requires-Dist: langchain-chroma>=0.1.0; extra == 'all'
Requires-Dist: langchain-community>=0.2.0; extra == 'all'
Requires-Dist: tiktoken>=0.5.0; extra == 'all'
Requires-Dist: tqdm>=4.66.0; extra == 'all'
Provides-Extra: rag
Requires-Dist: beautifulsoup4>=4.12.0; extra == 'rag'
Requires-Dist: certifi>=2023.0.0; extra == 'rag'
Requires-Dist: chromadb>=0.4.0; extra == 'rag'
Requires-Dist: langchain-chroma>=0.1.0; extra == 'rag'
Requires-Dist: langchain-community>=0.2.0; extra == 'rag'
Requires-Dist: tiktoken>=0.5.0; extra == 'rag'
Requires-Dist: tqdm>=4.66.0; extra == 'rag'
